{
    "type":"origins:action_over_time", 
    "entity_action":{
        "type":"origins:and",
        "actions": [
        {
            "type": "origins:apply_effect",
            "effect": "minecraft:resistance",
            "duration": 20,
            "amplifier": 2
        },
        {
            "type": "origins:apply_effect",
            "effect": "minecraft:strength",
            "duration": 20,
            "amplifier": 1
        }
    ] 
    },
    "interval": 20,
    "condition":{
    "type":"origins:and",
            "conditions":[
            {
                "type": "origins:submerged_in",
                "fluid": "minecraft:water"
            },
            {
                "type": "origins:power_active",
                "power": "chill:banana/toggle_toggle"
            }
        ]
    },
    "hidden":true
}